mumuplayer12newinstances/README.MD
mumuplayer12newinstances/__init__.py
mumuplayer12newinstances/requirements.txt
mumuplayer12newinstances/thirdparty.json
mumuplayer12newinstances-0.10.dist-info/LICENSE.rst
mumuplayer12newinstances-0.10.dist-info/METADATA
mumuplayer12newinstances-0.10.dist-info/WHEEL
mumuplayer12newinstances-0.10.dist-info/top_level.txt
mumuplayer12newinstances-0.10.dist-info/RECORD
