Metadata-Version: 2.1
Name: mumuplayer12newinstances
Version: 0.10
Summary: Creates new instances of MuMu Player 12 with a copy of the entire system disk.
Home-page: https://github.com/hansalemaos/mumuplayer12newinstances
Author: Johannes Fischer
Author-email: aulasparticularesdealemaosp@gmail.com
License: MIT
Keywords: MuMu,instance
Classifier: Development Status :: 4 - Beta
Classifier: Programming Language :: Python :: 3 :: Only
Classifier: Programming Language :: Python :: 3.10
Classifier: Topic :: Software Development :: Libraries :: Python Modules
Classifier: Topic :: Utilities
License-File: LICENSE.rst
Requires-Dist: flatten-any-dict-iterable-or-whatsoever
Requires-Dist: killallappsinfolder
Requires-Dist: list-all-files-recursively-short
Requires-Dist: xmltodict
